pocus/__init__.py
pocus/__main__.py
pocus/php_installer.py
pocus/pocus.py
pocus-0.1.2.dist-info/METADATA
pocus-0.1.2.dist-info/WHEEL
pocus-0.1.2.dist-info/entry_points.txt
pocus-0.1.2.dist-info/RECORD
