Metadata-Version: 2.4
Name: pocus
Version: 0.1.2
Summary: A short description
Project-URL: Homepage, https://github.com/pronskiy/pocus
Author-email: Roman Pronskiy <roman@pronskiy.com>
License: MIT
Requires-Python: >=3.8
Requires-Dist: requests
